futu/__init__.py
futu/_version.py
futu/tests/__init__.py
futu/tests/conftest.py
futu/tests/test_examples.py
futu-0.0.1.dist-info/AUTHORS.rst
futu-0.0.1.dist-info/LICENSE
futu-0.0.1.dist-info/METADATA
futu-0.0.1.dist-info/WHEEL
futu-0.0.1.dist-info/entry_points.txt
futu-0.0.1.dist-info/top_level.txt
futu-0.0.1.dist-info/RECORD
